gyvatukas/__init__.py
gyvatukas/exceptions.py
gyvatukas/internal.py
gyvatukas/services/iptoolkit.py
gyvatukas/utils/bool.py
gyvatukas/utils/crypto.py
gyvatukas/utils/decorators.py
gyvatukas/utils/dict_.py
gyvatukas/utils/dt.py
gyvatukas/utils/env.py
gyvatukas/utils/fs.py
gyvatukas/utils/generators.py
gyvatukas/utils/image.py
gyvatukas/utils/ip.py
gyvatukas/utils/json_.py
gyvatukas/utils/lithuania.py
gyvatukas/utils/simplestore.py
gyvatukas/utils/sql.py
gyvatukas/utils/string_.py
gyvatukas/utils/validators.py
gyvatukas/www/github_com.py
gyvatukas/www/mano_eso_lt.py
gyvatukas/www/meteo_lt.py
gyvatukas/www/nominatim_org.py
gyvatukas/www/ntfy_sh.py
gyvatukas/www/openrouter_ai.py
gyvatukas/www/powerhitradio_lt.py
gyvatukas-25.dist-info/METADATA
gyvatukas-25.dist-info/WHEEL
gyvatukas-25.dist-info/RECORD
