Metadata-Version: 2.3
Name: gyvatukas
Version: 25
Summary: See README.md
Author: Paulius
Author-email: dev@paulius.xyz
Requires-Python: >=3.12
Classifier: Programming Language :: Python :: 3
Classifier: Programming Language :: Python :: 3.12
Classifier: Programming Language :: Python :: 3.13
Requires-Dist: Pillow (>=12,<13)
Requires-Dist: bcrypt (>=5,<6)
Requires-Dist: beautifulsoup4 (>=4,<5)
Requires-Dist: diskcache (>=5,<6)
Requires-Dist: emval (>=0.1,<0.2)
Requires-Dist: httpx (>=0,<1)
Requires-Dist: platformdirs (>=4,<5)
Requires-Dist: pydantic (>=2,<3)
Project-URL: Documentation, https://pauliusbaulius.github.io/gyvatukas/gyvatukas/
Project-URL: Repository, https://github.com/pauliusbaulius/gyvatukas
